tintervals/__init__.py
tintervals/cirt.py
tintervals/conversion.py
tintervals/deadtime.py
tintervals/intervals.py
tintervals/rocitlinks.py
tintervals-0.2.0.dist-info/LICENSE
tintervals-0.2.0.dist-info/METADATA
tintervals-0.2.0.dist-info/WHEEL
tintervals-0.2.0.dist-info/RECORD
