Metadata-Version: 2.1
Name: tintervals
Version: 0.2.0
Summary: A collection of tools to work with time intervals and to convert time data
License: MIT
Author: Marco Pizzocaro
Author-email: m.pizzocaro@inrim.it
Requires-Python: >=3.10,<4.0
Classifier: License :: OSI Approved :: MIT License
Classifier: Programming Language :: Python :: 3
Classifier: Programming Language :: Python :: 3.10
Classifier: Programming Language :: Python :: 3.11
Classifier: Programming Language :: Python :: 3.12
Requires-Dist: ciso8601 (>=2.3.2,<3.0.0)
Requires-Dist: matplotlib (>=3.9.2,<4.0.0)
Requires-Dist: numpy (>=2.0.1,<3.0.0)
Requires-Dist: pandas (>=2.2.2,<3.0.0)
Requires-Dist: pyyaml (>=6.0.2,<7.0.0)
Requires-Dist: scipy (>=1.14.1,<2.0.0)
